kahoot_to_anki/__init__.py
kahoot_to_anki/cli.py
kahoot_to_anki/main.py
kahoot_to_anki/processing.py
kahoot_to_anki-1.2.0.dist-info/licenses/LICENSE
tests/__init__.py
tests/test_cli.py
tests/test_processing.py
kahoot_to_anki-1.2.0.dist-info/METADATA
kahoot_to_anki-1.2.0.dist-info/WHEEL
kahoot_to_anki-1.2.0.dist-info/entry_points.txt
kahoot_to_anki-1.2.0.dist-info/top_level.txt
kahoot_to_anki-1.2.0.dist-info/RECORD
