Metadata-Version: 2.4
Name: kahoot-to-anki
Version: 1.2.0
Summary: CLI tool to convert Kahoot quiz reports into Anki flashcards
Author: Simon Hardmeier
License-Expression: MIT
Requires-Python: >=3.9
License-File: LICENSE
Requires-Dist: genanki
Requires-Dist: pandas
Requires-Dist: openpyxl
Dynamic: license-file
